{"type":"Topology","objects":{"fossils_Stage_3":{"type":"GeometryCollection","interval_name":"Stage 3","age_bottom":521,"age_top":514,"geometries":[{"type":"Point","properties":{"occ":8},"coordinates":[2289,348]},{"type":"Point","properties":{"occ":6},"coordinates":[6379,9313]},{"type":"Point","properties":{"occ":4},"coordinates":[2696,311]},{"type":"Point","properties":{"occ":39},"coordinates":[5901,491]},{"type":"Point","properties":{"occ":5},"coordinates":[2296,912]},{"type":"Point","properties":{"occ":14},"coordinates":[6651,2082]},{"type":"Point","properties":{"occ":54},"coordinates":[5901,491]},{"type":"Point","properties":{"occ":14},"coordinates":[2696,311]},{"type":"Point","properties":{"occ":5},"coordinates":[2296,912]},{"type":"Point","properties":{"occ":3},"coordinates":[6320,1000]},{"type":"Point","properties":{"occ":6},"coordinates":[2849,1605]},{"type":"Point","properties":{"occ":1},"coordinates":[2514,522]},{"type":"Point","properties":{"occ":5},"coordinates":[2469,431]},{"type":"Point","properties":{"occ":14},"coordinates":[2334,630]},{"type":"Point","properties":{"occ":2},"coordinates":[1171,5222]},{"type":"Point","properties":{"occ":1},"coordinates":[6296,1133]},{"type":"Point","properties":{"occ":3},"coordinates":[6608,1617]},{"type":"Point","properties":{"occ":7},"coordinates":[2310,616]},{"type":"Point","properties":{"occ":9},"coordinates":[2145,1057]},{"type":"Point","properties":{"occ":10},"coordinates":[2457,239]},{"type":"Point","properties":{"occ":6},"coordinates":[2509,123]},{"type":"Point","properties":{"occ":2},"coordinates":[2263,643]},{"type":"Point","properties":{"occ":1},"coordinates":[2619,713]},{"type":"Point","properties":{"occ":1},"coordinates":[2619,713]},{"type":"Point","properties":{"occ":1},"coordinates":[2619,713]},{"type":"Point","properties":{"occ":1},"coordinates":[2619,709]},{"type":"Point","properties":{"occ":2},"coordinates":[2619,709]},{"type":"Point","properties":{"occ":2},"coordinates":[2619,709]},{"type":"Point","properties":{"occ":1},"coordinates":[2619,710]},{"type":"Point","properties":{"occ":2},"coordinates":[2619,708]},{"type":"Point","properties":{"occ":2},"coordinates":[2619,708]},{"type":"Point","properties":{"occ":2},"coordinates":[2619,708]},{"type":"Point","properties":{"occ":2},"coordinates":[2619,704]},{"type":"Point","properties":{"occ":1},"coordinates":[2632,718]},{"type":"Point","properties":{"occ":1},"coordinates":[2632,718]},{"type":"Point","properties":{"occ":1},"coordinates":[2624,679]},{"type":"Point","properties":{"occ":1},"coordinates":[2624,679]},{"type":"Point","properties":{"occ":1},"coordinates":[2624,679]},{"type":"Point","properties":{"occ":1},"coordinates":[2624,679]},{"type":"Point","properties":{"occ":1},"coordinates":[2628,654]},{"type":"Point","properties":{"occ":1},"coordinates":[2628,654]},{"type":"Point","properties":{"occ":2},"coordinates":[2628,654]},{"type":"Point","properties":{"occ":1},"coordinates":[2604,649]},{"type":"Point","properties":{"occ":1},"coordinates":[2604,649]},{"type":"Point","properties":{"occ":1},"coordinates":[2604,649]},{"type":"Point","properties":{"occ":3},"coordinates":[2604,649]},{"type":"Point","properties":{"occ":1},"coordinates":[2604,649]},{"type":"Point","properties":{"occ":3},"coordinates":[2604,649]},{"type":"Point","properties":{"occ":1},"coordinates":[2605,646]},{"type":"Point","properties":{"occ":1},"coordinates":[2641,651]},{"type":"Point","properties":{"occ":1},"coordinates":[2641,651]},{"type":"Point","properties":{"occ":1},"coordinates":[2641,651]},{"type":"Point","properties":{"occ":1},"coordinates":[2641,651]},{"type":"Point","properties":{"occ":1},"coordinates":[2601,630]},{"type":"Point","properties":{"occ":1},"coordinates":[2601,630]},{"type":"Point","properties":{"occ":1},"coordinates":[2602,606]},{"type":"Point","properties":{"occ":1},"coordinates":[2602,606]},{"type":"Point","properties":{"occ":3},"coordinates":[2602,606]},{"type":"Point","properties":{"occ":2},"coordinates":[2620,713]},{"type":"Point","properties":{"occ":3},"coordinates":[2620,713]},{"type":"Point","properties":{"occ":5},"coordinates":[2639,709]},{"type":"Point","properties":{"occ":5},"coordinates":[2639,709]},{"type":"Point","properties":{"occ":7},"coordinates":[2638,711]},{"type":"Point","properties":{"occ":1},"coordinates":[2625,678]},{"type":"Point","properties":{"occ":2},"coordinates":[2625,678]},{"type":"Point","properties":{"occ":3},"coordinates":[2625,678]},{"type":"Point","properties":{"occ":1},"coordinates":[2625,678]},{"type":"Point","properties":{"occ":2},"coordinates":[2625,678]},{"type":"Point","properties":{"occ":4},"coordinates":[2625,678]},{"type":"Point","properties":{"occ":2},"coordinates":[2625,678]},{"type":"Point","properties":{"occ":1},"coordinates":[2641,651]},{"type":"Point","properties":{"occ":2},"coordinates":[2641,651]},{"type":"Point","properties":{"occ":4},"coordinates":[2641,651]},{"type":"Point","properties":{"occ":2},"coordinates":[2641,651]},{"type":"Point","properties":{"occ":2},"coordinates":[2641,651]},{"type":"Point","properties":{"occ":2},"coordinates":[2641,651]},{"type":"Point","properties":{"occ":3},"coordinates":[2641,651]},{"type":"Point","properties":{"occ":3},"coordinates":[2602,630]},{"type":"Point","properties":{"occ":5},"coordinates":[2602,630]},{"type":"Point","properties":{"occ":2},"coordinates":[2634,714]},{"type":"Point","properties":{"occ":4},"coordinates":[2619,709]},{"type":"Point","properties":{"occ":4},"coordinates":[2602,630]},{"type":"Point","properties":{"occ":2},"coordinates":[2602,630]},{"type":"Point","properties":{"occ":4},"coordinates":[2634,714]},{"type":"Point","properties":{"occ":4},"coordinates":[2601,631]},{"type":"Point","properties":{"occ":7},"coordinates":[2601,631]},{"type":"Point","properties":{"occ":5},"coordinates":[2601,631]},{"type":"Point","properties":{"occ":5},"coordinates":[2601,631]},{"type":"Point","properties":{"occ":6},"coordinates":[2601,631]},{"type":"Point","properties":{"occ":5},"coordinates":[2601,631]},{"type":"Point","properties":{"occ":2},"coordinates":[2601,631]},{"type":"Point","properties":{"occ":4},"coordinates":[2601,631]},{"type":"Point","properties":{"occ":4},"coordinates":[2601,631]},{"type":"Point","properties":{"occ":3},"coordinates":[2602,607]},{"type":"Point","properties":{"occ":3},"coordinates":[2619,709]},{"type":"Point","properties":{"occ":4},"coordinates":[2619,709]},{"type":"Point","properties":{"occ":3},"coordinates":[2619,709]},{"type":"Point","properties":{"occ":5},"coordinates":[2619,709]},{"type":"Point","properties":{"occ":3},"coordinates":[2619,709]},{"type":"Point","properties":{"occ":4},"coordinates":[2620,700]},{"type":"Point","properties":{"occ":8},"coordinates":[2620,699]},{"type":"Point","properties":{"occ":5},"coordinates":[2620,699]},{"type":"Point","properties":{"occ":6},"coordinates":[2620,699]},{"type":"Point","properties":{"occ":3},"coordinates":[2619,705]},{"type":"Point","properties":{"occ":5},"coordinates":[2602,625]},{"type":"Point","properties":{"occ":7},"coordinates":[2602,625]},{"type":"Point","properties":{"occ":3},"coordinates":[2620,699]},{"type":"Point","properties":{"occ":6},"coordinates":[2620,699]},{"type":"Point","properties":{"occ":3},"coordinates":[2620,699]},{"type":"Point","properties":{"occ":5},"coordinates":[2620,699]},{"type":"Point","properties":{"occ":7},"coordinates":[2620,699]},{"type":"Point","properties":{"occ":3},"coordinates":[2620,699]},{"type":"Point","properties":{"occ":2},"coordinates":[2620,699]},{"type":"Point","properties":{"occ":3},"coordinates":[2620,699]},{"type":"Point","properties":{"occ":3},"coordinates":[2620,699]},{"type":"Point","properties":{"occ":7},"coordinates":[2620,699]},{"type":"Point","properties":{"occ":5},"coordinates":[2620,699]},{"type":"Point","properties":{"occ":5},"coordinates":[2620,704]},{"type":"Point","properties":{"occ":3},"coordinates":[2620,700]},{"type":"Point","properties":{"occ":3},"coordinates":[2620,700]},{"type":"Point","properties":{"occ":7},"coordinates":[2620,700]},{"type":"Point","properties":{"occ":2},"coordinates":[1339,6132]},{"type":"Point","properties":{"occ":1},"coordinates":[2273,619]},{"type":"Point","properties":{"occ":3},"coordinates":[2145,1057]},{"type":"Point","properties":{"occ":4},"coordinates":[2145,1057]},{"type":"Point","properties":{"occ":2},"coordinates":[2145,1057]},{"type":"Point","properties":{"occ":4},"coordinates":[2581,354]},{"type":"Point","properties":{"occ":6},"coordinates":[2295,517]},{"type":"Point","properties":{"occ":5},"coordinates":[2624,682]},{"type":"Point","properties":{"occ":6},"coordinates":[2604,650]},{"type":"Point","properties":{"occ":4},"coordinates":[2604,650]},{"type":"Point","properties":{"occ":2},"coordinates":[5955,179]},{"type":"Point","properties":{"occ":2},"coordinates":[5950,139]},{"type":"Point","properties":{"occ":2},"coordinates":[5953,142]},{"type":"Point","properties":{"occ":6},"coordinates":[2359,687]},{"type":"Point","properties":{"occ":3},"coordinates":[2359,687]},{"type":"Point","properties":{"occ":4},"coordinates":[2315,667]},{"type":"Point","properties":{"occ":1},"coordinates":[2315,667]},{"type":"Point","properties":{"occ":8},"coordinates":[2315,667]},{"type":"Point","properties":{"occ":1},"coordinates":[2315,667]},{"type":"Point","properties":{"occ":7},"coordinates":[2315,667]},{"type":"Point","properties":{"occ":13},"coordinates":[2622,689]},{"type":"Point","properties":{"occ":5},"coordinates":[2607,633]},{"type":"Point","properties":{"occ":9},"coordinates":[2607,633]},{"type":"Point","properties":{"occ":2},"coordinates":[2607,633]},{"type":"Point","properties":{"occ":2},"coordinates":[2607,633]},{"type":"Point","properties":{"occ":6},"coordinates":[2315,667]},{"type":"Point","properties":{"occ":3},"coordinates":[2315,667]},{"type":"Point","properties":{"occ":1},"coordinates":[2315,667]},{"type":"Point","properties":{"occ":13},"coordinates":[2344,673]},{"type":"Point","properties":{"occ":3},"coordinates":[2344,673]},{"type":"Point","properties":{"occ":3},"coordinates":[2344,673]},{"type":"Point","properties":{"occ":2},"coordinates":[2344,673]},{"type":"Point","properties":{"occ":1},"coordinates":[2344,673]},{"type":"Point","properties":{"occ":5},"coordinates":[2462,281]},{"type":"Point","properties":{"occ":3},"coordinates":[2462,281]},{"type":"Point","properties":{"occ":3},"coordinates":[2462,281]},{"type":"Point","properties":{"occ":3},"coordinates":[2462,281]},{"type":"Point","properties":{"occ":3},"coordinates":[2462,281]},{"type":"Point","properties":{"occ":5},"coordinates":[2462,281]},{"type":"Point","properties":{"occ":3},"coordinates":[2462,281]},{"type":"Point","properties":{"occ":4},"coordinates":[2462,281]},{"type":"Point","properties":{"occ":4},"coordinates":[2462,281]},{"type":"Point","properties":{"occ":6},"coordinates":[2462,281]},{"type":"Point","properties":{"occ":9},"coordinates":[2462,281]},{"type":"Point","properties":{"occ":7},"coordinates":[2462,281]},{"type":"Point","properties":{"occ":5},"coordinates":[2462,281]},{"type":"Point","properties":{"occ":6},"coordinates":[2462,281]},{"type":"Point","properties":{"occ":10},"coordinates":[2462,281]},{"type":"Point","properties":{"occ":3},"coordinates":[2462,281]},{"type":"Point","properties":{"occ":4},"coordinates":[2462,281]},{"type":"Point","properties":{"occ":4},"coordinates":[2462,281]},{"type":"Point","properties":{"occ":2},"coordinates":[2462,281]},{"type":"Point","properties":{"occ":3},"coordinates":[2462,281]},{"type":"Point","properties":{"occ":6},"coordinates":[2462,281]},{"type":"Point","properties":{"occ":6},"coordinates":[2462,281]},{"type":"Point","properties":{"occ":5},"coordinates":[2462,281]},{"type":"Point","properties":{"occ":1},"coordinates":[2169,3867]},{"type":"Point","properties":{"occ":1},"coordinates":[2169,3867]},{"type":"Point","properties":{"occ":1},"coordinates":[2169,3867]},{"type":"Point","properties":{"occ":1},"coordinates":[2169,3867]},{"type":"Point","properties":{"occ":1},"coordinates":[2169,3867]},{"type":"Point","properties":{"occ":3},"coordinates":[2169,3867]},{"type":"Point","properties":{"occ":11},"coordinates":[2176,3900]},{"type":"Point","properties":{"occ":1},"coordinates":[2178,3899]},{"type":"Point","properties":{"occ":1},"coordinates":[2178,3899]},{"type":"Point","properties":{"occ":1},"coordinates":[2178,3899]},{"type":"Point","properties":{"occ":1},"coordinates":[2178,3899]},{"type":"Point","properties":{"occ":1},"coordinates":[2178,3899]},{"type":"Point","properties":{"occ":1},"coordinates":[2178,3899]},{"type":"Point","properties":{"occ":2},"coordinates":[2178,3899]},{"type":"Point","properties":{"occ":1},"coordinates":[2178,3899]},{"type":"Point","properties":{"occ":4},"coordinates":[2178,3899]},{"type":"Point","properties":{"occ":6},"coordinates":[5902,491]},{"type":"Point","properties":{"occ":2},"coordinates":[7350,2250]},{"type":"Point","properties":{"occ":1},"coordinates":[7350,2250]},{"type":"Point","properties":{"occ":1},"coordinates":[7350,2250]},{"type":"Point","properties":{"occ":2},"coordinates":[7350,2250]},{"type":"Point","properties":{"occ":1},"coordinates":[7350,2250]},{"type":"Point","properties":{"occ":1},"coordinates":[7350,2250]},{"type":"Point","properties":{"occ":2},"coordinates":[7350,2250]},{"type":"Point","properties":{"occ":2},"coordinates":[7350,2250]},{"type":"Point","properties":{"occ":2},"coordinates":[7350,2250]},{"type":"Point","properties":{"occ":2},"coordinates":[7350,2250]},{"type":"Point","properties":{"occ":1},"coordinates":[7350,2250]},{"type":"Point","properties":{"occ":1},"coordinates":[7350,2250]},{"type":"Point","properties":{"occ":1},"coordinates":[7350,2250]},{"type":"Point","properties":{"occ":1},"coordinates":[7350,2250]},{"type":"Point","properties":{"occ":1},"coordinates":[7350,2250]},{"type":"Point","properties":{"occ":2},"coordinates":[7350,2250]},{"type":"Point","properties":{"occ":1},"coordinates":[7350,2250]},{"type":"Point","properties":{"occ":8},"coordinates":[2363,671]},{"type":"Point","properties":{"occ":5},"coordinates":[6623,2143]},{"type":"Point","properties":{"occ":27},"coordinates":[6647,2025]},{"type":"Point","properties":{"occ":17},"coordinates":[6629,2109]},{"type":"Point","properties":{"occ":4},"coordinates":[1193,6062]},{"type":"Point","properties":{"occ":5},"coordinates":[1193,6062]},{"type":"Point","properties":{"occ":4},"coordinates":[1193,6062]},{"type":"Point","properties":{"occ":7},"coordinates":[1162,6055]},{"type":"Point","properties":{"occ":7},"coordinates":[1424,6251]},{"type":"Point","properties":{"occ":6},"coordinates":[2620,703]},{"type":"Point","properties":{"occ":8},"coordinates":[2622,708]},{"type":"Point","properties":{"occ":7},"coordinates":[2622,708]},{"type":"Point","properties":{"occ":2},"coordinates":[2622,708]},{"type":"Point","properties":{"occ":6},"coordinates":[2622,708]},{"type":"Point","properties":{"occ":8},"coordinates":[2622,708]},{"type":"Point","properties":{"occ":4},"coordinates":[2622,708]},{"type":"Point","properties":{"occ":5},"coordinates":[2622,708]},{"type":"Point","properties":{"occ":7},"coordinates":[2622,708]},{"type":"Point","properties":{"occ":5},"coordinates":[2622,708]},{"type":"Point","properties":{"occ":6},"coordinates":[2622,708]},{"type":"Point","properties":{"occ":6},"coordinates":[2634,714]},{"type":"Point","properties":{"occ":4},"coordinates":[2634,714]},{"type":"Point","properties":{"occ":5},"coordinates":[2634,714]},{"type":"Point","properties":{"occ":4},"coordinates":[2634,714]},{"type":"Point","properties":{"occ":6},"coordinates":[2638,711]},{"type":"Point","properties":{"occ":3},"coordinates":[2638,711]},{"type":"Point","properties":{"occ":4},"coordinates":[2638,711]},{"type":"Point","properties":{"occ":4},"coordinates":[2638,710]},{"type":"Point","properties":{"occ":8},"coordinates":[2638,710]},{"type":"Point","properties":{"occ":6},"coordinates":[2630,719]},{"type":"Point","properties":{"occ":4},"coordinates":[1339,6132]},{"type":"Point","properties":{"occ":4},"coordinates":[2619,708]},{"type":"Point","properties":{"occ":7},"coordinates":[2619,708]},{"type":"Point","properties":{"occ":5},"coordinates":[2619,708]},{"type":"Point","properties":{"occ":4},"coordinates":[2619,708]},{"type":"Point","properties":{"occ":2},"coordinates":[2619,708]},{"type":"Point","properties":{"occ":4},"coordinates":[2619,708]},{"type":"Point","properties":{"occ":5},"coordinates":[2620,705]},{"type":"Point","properties":{"occ":4},"coordinates":[2620,705]},{"type":"Point","properties":{"occ":2},"coordinates":[2620,705]},{"type":"Point","properties":{"occ":6},"coordinates":[2619,705]},{"type":"Point","properties":{"occ":1},"coordinates":[2620,704]},{"type":"Point","properties":{"occ":4},"coordinates":[2620,704]},{"type":"Point","properties":{"occ":2},"coordinates":[2620,704]},{"type":"Point","properties":{"occ":2},"coordinates":[2620,700]},{"type":"Point","properties":{"occ":5},"coordinates":[2620,700]},{"type":"Point","properties":{"occ":4},"coordinates":[2620,702]},{"type":"Point","properties":{"occ":3},"coordinates":[2620,703]},{"type":"Point","properties":{"occ":5},"coordinates":[2620,703]},{"type":"Point","properties":{"occ":6},"coordinates":[2625,679]},{"type":"Point","properties":{"occ":10},"coordinates":[2625,679]},{"type":"Point","properties":{"occ":4},"coordinates":[2625,679]},{"type":"Point","properties":{"occ":6},"coordinates":[2625,679]},{"type":"Point","properties":{"occ":4},"coordinates":[2625,679]},{"type":"Point","properties":{"occ":2},"coordinates":[2625,679]},{"type":"Point","properties":{"occ":4},"coordinates":[2625,679]},{"type":"Point","properties":{"occ":6},"coordinates":[2625,679]},{"type":"Point","properties":{"occ":6},"coordinates":[2628,654]},{"type":"Point","properties":{"occ":3},"coordinates":[2628,654]},{"type":"Point","properties":{"occ":25},"coordinates":[8149,3151]},{"type":"Point","properties":{"occ":1},"coordinates":[2386,730]},{"type":"Point","properties":{"occ":5},"coordinates":[6829,1572]},{"type":"Point","properties":{"occ":1},"coordinates":[6829,1572]},{"type":"Point","properties":{"occ":4},"coordinates":[6829,1572]},{"type":"Point","properties":{"occ":5},"coordinates":[6829,1572]},{"type":"Point","properties":{"occ":5},"coordinates":[6839,1555]},{"type":"Point","properties":{"occ":11},"coordinates":[6839,1555]},{"type":"Point","properties":{"occ":6},"coordinates":[6839,1555]},{"type":"Point","properties":{"occ":7},"coordinates":[6839,1555]},{"type":"Point","properties":{"occ":6},"coordinates":[6874,1655]},{"type":"Point","properties":{"occ":9},"coordinates":[6839,1555]},{"type":"Point","properties":{"occ":5},"coordinates":[6874,1655]},{"type":"Point","properties":{"occ":11},"coordinates":[6871,1610]},{"type":"Point","properties":{"occ":3},"coordinates":[6871,1610]},{"type":"Point","properties":{"occ":7},"coordinates":[6839,1555]},{"type":"Point","properties":{"occ":9},"coordinates":[6839,1555]},{"type":"Point","properties":{"occ":3},"coordinates":[6839,1555]},{"type":"Point","properties":{"occ":8},"coordinates":[6839,1555]},{"type":"Point","properties":{"occ":3},"coordinates":[6839,1555]},{"type":"Point","properties":{"occ":4},"coordinates":[6839,1555]},{"type":"Point","properties":{"occ":3},"coordinates":[6839,1555]},{"type":"Point","properties":{"occ":4},"coordinates":[6839,1555]},{"type":"Point","properties":{"occ":9},"coordinates":[6839,1555]},{"type":"Point","properties":{"occ":5},"coordinates":[2359,595]},{"type":"Point","properties":{"occ":4},"coordinates":[2328,689]},{"type":"Point","properties":{"occ":5},"coordinates":[2328,689]},{"type":"Point","properties":{"occ":2},"coordinates":[7399,2264]},{"type":"Point","properties":{"occ":4},"coordinates":[7451,2191]},{"type":"Point","properties":{"occ":2},"coordinates":[7399,2264]},{"type":"Point","properties":{"occ":2},"coordinates":[7399,2264]},{"type":"Point","properties":{"occ":1},"coordinates":[31,6358]},{"type":"Point","properties":{"occ":1},"coordinates":[7399,2264]},{"type":"Point","properties":{"occ":5},"coordinates":[31,6358]},{"type":"Point","properties":{"occ":2},"coordinates":[2328,689]},{"type":"Point","properties":{"occ":23},"coordinates":[6624,2143]},{"type":"Point","properties":{"occ":8},"coordinates":[0,6354]},{"type":"Point","properties":{"occ":3},"coordinates":[49,6365]},{"type":"Point","properties":{"occ":2},"coordinates":[29,6354]},{"type":"Point","properties":{"occ":2},"coordinates":[49,6365]},{"type":"Point","properties":{"occ":6},"coordinates":[49,6365]},{"type":"Point","properties":{"occ":3},"coordinates":[29,6354]},{"type":"Point","properties":{"occ":3},"coordinates":[2342,670]},{"type":"Point","properties":{"occ":4},"coordinates":[2342,670]},{"type":"Point","properties":{"occ":2},"coordinates":[2342,670]},{"type":"Point","properties":{"occ":3},"coordinates":[2342,670]},{"type":"Point","properties":{"occ":2},"coordinates":[2342,670]},{"type":"Point","properties":{"occ":2},"coordinates":[2342,670]},{"type":"Point","properties":{"occ":2},"coordinates":[2342,670]},{"type":"Point","properties":{"occ":1},"coordinates":[2342,670]},{"type":"Point","properties":{"occ":1},"coordinates":[2342,670]},{"type":"Point","properties":{"occ":1},"coordinates":[2342,670]},{"type":"Point","properties":{"occ":1},"coordinates":[2342,670]},{"type":"Point","properties":{"occ":2},"coordinates":[2342,670]},{"type":"Point","properties":{"occ":1},"coordinates":[2342,670]},{"type":"Point","properties":{"occ":2},"coordinates":[2342,670]},{"type":"Point","properties":{"occ":2},"coordinates":[2342,670]},{"type":"Point","properties":{"occ":1},"coordinates":[2342,670]},{"type":"Point","properties":{"occ":1},"coordinates":[2342,670]},{"type":"Point","properties":{"occ":4},"coordinates":[2342,670]},{"type":"Point","properties":{"occ":1},"coordinates":[2342,670]},{"type":"Point","properties":{"occ":1},"coordinates":[2342,670]},{"type":"Point","properties":{"occ":3},"coordinates":[2342,670]},{"type":"Point","properties":{"occ":1},"coordinates":[2342,670]},{"type":"Point","properties":{"occ":3},"coordinates":[2342,670]},{"type":"Point","properties":{"occ":1},"coordinates":[2342,670]},{"type":"Point","properties":{"occ":1},"coordinates":[2342,670]},{"type":"Point","properties":{"occ":3},"coordinates":[2342,670]},{"type":"Point","properties":{"occ":1},"coordinates":[2342,670]},{"type":"Point","properties":{"occ":1},"coordinates":[2342,670]},{"type":"Point","properties":{"occ":4},"coordinates":[2342,670]},{"type":"Point","properties":{"occ":1},"coordinates":[2342,670]},{"type":"Point","properties":{"occ":2},"coordinates":[2342,670]},{"type":"Point","properties":{"occ":3},"coordinates":[2342,670]},{"type":"Point","properties":{"occ":3},"coordinates":[2342,670]},{"type":"Point","properties":{"occ":1},"coordinates":[2342,670]},{"type":"Point","properties":{"occ":4},"coordinates":[2342,670]},{"type":"Point","properties":{"occ":2},"coordinates":[2342,670]},{"type":"Point","properties":{"occ":3},"coordinates":[2342,670]},{"type":"Point","properties":{"occ":1},"coordinates":[2342,670]},{"type":"Point","properties":{"occ":3},"coordinates":[2342,670]},{"type":"Point","properties":{"occ":1},"coordinates":[2342,670]},{"type":"Point","properties":{"occ":4},"coordinates":[2342,670]},{"type":"Point","properties":{"occ":1},"coordinates":[2342,670]},{"type":"Point","properties":{"occ":1},"coordinates":[2342,670]},{"type":"Point","properties":{"occ":2},"coordinates":[2342,670]},{"type":"Point","properties":{"occ":2},"coordinates":[2342,670]},{"type":"Point","properties":{"occ":2},"coordinates":[2342,670]},{"type":"Point","properties":{"occ":3},"coordinates":[2342,670]},{"type":"Point","properties":{"occ":8},"coordinates":[2342,670]},{"type":"Point","properties":{"occ":2},"coordinates":[2342,670]},{"type":"Point","properties":{"occ":2},"coordinates":[2342,670]},{"type":"Point","properties":{"occ":2},"coordinates":[2342,670]},{"type":"Point","properties":{"occ":2},"coordinates":[2342,670]},{"type":"Point","properties":{"occ":2},"coordinates":[2342,670]},{"type":"Point","properties":{"occ":2},"coordinates":[2342,670]},{"type":"Point","properties":{"occ":5},"coordinates":[2362,654]},{"type":"Point","properties":{"occ":6},"coordinates":[2334,633]},{"type":"Point","properties":{"occ":1},"coordinates":[2334,633]},{"type":"Point","properties":{"occ":1},"coordinates":[2334,633]},{"type":"Point","properties":{"occ":1},"coordinates":[2334,633]},{"type":"Point","properties":{"occ":2},"coordinates":[2362,654]},{"type":"Point","properties":{"occ":1},"coordinates":[2362,654]},{"type":"Point","properties":{"occ":1},"coordinates":[2362,654]},{"type":"Point","properties":{"occ":1},"coordinates":[2362,654]},{"type":"Point","properties":{"occ":2},"coordinates":[2362,654]},{"type":"Point","properties":{"occ":1},"coordinates":[2362,654]},{"type":"Point","properties":{"occ":3},"coordinates":[2362,654]},{"type":"Point","properties":{"occ":2},"coordinates":[2362,654]},{"type":"Point","properties":{"occ":1},"coordinates":[2362,654]},{"type":"Point","properties":{"occ":1},"coordinates":[2362,654]},{"type":"Point","properties":{"occ":2},"coordinates":[2362,654]},{"type":"Point","properties":{"occ":2},"coordinates":[2362,654]},{"type":"Point","properties":{"occ":2},"coordinates":[2362,654]},{"type":"Point","properties":{"occ":6},"coordinates":[2362,654]},{"type":"Point","properties":{"occ":1},"coordinates":[2362,654]},{"type":"Point","properties":{"occ":3},"coordinates":[2362,654]},{"type":"Point","properties":{"occ":3},"coordinates":[2309,525]},{"type":"Point","properties":{"occ":3},"coordinates":[2309,525]},{"type":"Point","properties":{"occ":3},"coordinates":[2309,525]},{"type":"Point","properties":{"occ":3},"coordinates":[2309,525]},{"type":"Point","properties":{"occ":3},"coordinates":[2309,525]},{"type":"Point","properties":{"occ":2},"coordinates":[2309,525]},{"type":"Point","properties":{"occ":7},"coordinates":[2309,525]},{"type":"Point","properties":{"occ":3},"coordinates":[2309,525]},{"type":"Point","properties":{"occ":1},"coordinates":[2309,525]},{"type":"Point","properties":{"occ":1},"coordinates":[2309,525]},{"type":"Point","properties":{"occ":2},"coordinates":[2309,525]},{"type":"Point","properties":{"occ":3},"coordinates":[2309,525]},{"type":"Point","properties":{"occ":3},"coordinates":[2309,525]},{"type":"Point","properties":{"occ":4},"coordinates":[2309,525]},{"type":"Point","properties":{"occ":6},"coordinates":[2309,525]},{"type":"Point","properties":{"occ":2},"coordinates":[2309,525]},{"type":"Point","properties":{"occ":12},"coordinates":[8160,3134]},{"type":"Point","properties":{"occ":6},"coordinates":[8160,3134]},{"type":"Point","properties":{"occ":6},"coordinates":[8160,3134]},{"type":"Point","properties":{"occ":5},"coordinates":[8160,3134]},{"type":"Point","properties":{"occ":1},"coordinates":[8580,2942]},{"type":"Point","properties":{"occ":24},"coordinates":[1237,6104]},{"type":"Point","properties":{"occ":7},"coordinates":[1237,6104]},{"type":"Point","properties":{"occ":9},"coordinates":[1213,6100]},{"type":"Point","properties":{"occ":19},"coordinates":[1213,6100]},{"type":"Point","properties":{"occ":12},"coordinates":[2341,609]},{"type":"Point","properties":{"occ":9},"coordinates":[5902,490]},{"type":"Point","properties":{"occ":20},"coordinates":[1438,4963]},{"type":"Point","properties":{"occ":5},"coordinates":[1487,4800]},{"type":"Point","properties":{"occ":1},"coordinates":[2176,3904]},{"type":"Point","properties":{"occ":4},"coordinates":[2274,584]},{"type":"Point","properties":{"occ":1},"coordinates":[5978,236]},{"type":"Point","properties":{"occ":2},"coordinates":[2352,675]},{"type":"Point","properties":{"occ":5},"coordinates":[2363,595]},{"type":"Point","properties":{"occ":1},"coordinates":[2272,588]},{"type":"Point","properties":{"occ":1},"coordinates":[2346,682]},{"type":"Point","properties":{"occ":1},"coordinates":[914,6242]},{"type":"Point","properties":{"occ":4},"coordinates":[6652,2095]},{"type":"Point","properties":{"occ":1},"coordinates":[2532,0]},{"type":"Point","properties":{"occ":18},"coordinates":[2351,596]},{"type":"Point","properties":{"occ":2},"coordinates":[9999,9999]},{"type":"Point","properties":{"occ":1},"coordinates":[9731,9975]},{"type":"Point","properties":{"occ":1},"coordinates":[9999,9999]},{"type":"Point","properties":{"occ":2},"coordinates":[8528,2786]},{"type":"Point","properties":{"occ":2},"coordinates":[8552,2850]},{"type":"Point","properties":{"occ":1},"coordinates":[8628,2722]},{"type":"Point","properties":{"occ":2},"coordinates":[2646,904]},{"type":"Point","properties":{"occ":2},"coordinates":[2646,904]},{"type":"Point","properties":{"occ":1},"coordinates":[2646,904]},{"type":"Point","properties":{"occ":1},"coordinates":[2646,904]},{"type":"Point","properties":{"occ":1},"coordinates":[2646,904]},{"type":"Point","properties":{"occ":1},"coordinates":[2646,904]},{"type":"Point","properties":{"occ":1},"coordinates":[2646,904]},{"type":"Point","properties":{"occ":1},"coordinates":[2646,904]},{"type":"Point","properties":{"occ":1},"coordinates":[2646,904]},{"type":"Point","properties":{"occ":2},"coordinates":[2646,904]},{"type":"Point","properties":{"occ":1},"coordinates":[2646,904]},{"type":"Point","properties":{"occ":1},"coordinates":[2646,904]},{"type":"Point","properties":{"occ":1},"coordinates":[2646,904]},{"type":"Point","properties":{"occ":3},"coordinates":[2646,904]},{"type":"Point","properties":{"occ":5},"coordinates":[2646,904]},{"type":"Point","properties":{"occ":1},"coordinates":[2646,904]},{"type":"Point","properties":{"occ":1},"coordinates":[2646,904]},{"type":"Point","properties":{"occ":5},"coordinates":[2646,904]},{"type":"Point","properties":{"occ":5},"coordinates":[2646,904]},{"type":"Point","properties":{"occ":5},"coordinates":[2646,904]},{"type":"Point","properties":{"occ":3},"coordinates":[2646,904]},{"type":"Point","properties":{"occ":3},"coordinates":[2646,904]},{"type":"Point","properties":{"occ":1},"coordinates":[6188,970]},{"type":"Point","properties":{"occ":3},"coordinates":[2367,650]},{"type":"Point","properties":{"occ":1},"coordinates":[6353,1165]},{"type":"Point","properties":{"occ":1},"coordinates":[6355,1165]},{"type":"Point","properties":{"occ":1},"coordinates":[6282,1141]},{"type":"Point","properties":{"occ":1},"coordinates":[6282,1141]},{"type":"Point","properties":{"occ":1},"coordinates":[6309,1130]},{"type":"Point","properties":{"occ":1},"coordinates":[6232,1096]},{"type":"Point","properties":{"occ":1},"coordinates":[6206,998]},{"type":"Point","properties":{"occ":1},"coordinates":[5844,483]},{"type":"Point","properties":{"occ":3},"coordinates":[2355,671]},{"type":"Point","properties":{"occ":2},"coordinates":[2355,671]},{"type":"Point","properties":{"occ":1},"coordinates":[2355,671]},{"type":"Point","properties":{"occ":1},"coordinates":[2355,671]},{"type":"Point","properties":{"occ":2},"coordinates":[2355,671]},{"type":"Point","properties":{"occ":2},"coordinates":[2355,671]},{"type":"Point","properties":{"occ":2},"coordinates":[2355,671]},{"type":"Point","properties":{"occ":3},"coordinates":[2355,671]},{"type":"Point","properties":{"occ":2},"coordinates":[2355,671]},{"type":"Point","properties":{"occ":2},"coordinates":[2355,671]},{"type":"Point","properties":{"occ":2},"coordinates":[2355,671]},{"type":"Point","properties":{"occ":2},"coordinates":[2355,671]},{"type":"Point","properties":{"occ":2},"coordinates":[2355,671]},{"type":"Point","properties":{"occ":1},"coordinates":[2355,671]},{"type":"Point","properties":{"occ":1},"coordinates":[2355,671]},{"type":"Point","properties":{"occ":2},"coordinates":[2355,671]},{"type":"Point","properties":{"occ":1},"coordinates":[2355,671]},{"type":"Point","properties":{"occ":2},"coordinates":[2355,671]},{"type":"Point","properties":{"occ":2},"coordinates":[2355,671]},{"type":"Point","properties":{"occ":1},"coordinates":[2355,671]},{"type":"Point","properties":{"occ":1},"coordinates":[2355,671]},{"type":"Point","properties":{"occ":1},"coordinates":[2355,671]},{"type":"Point","properties":{"occ":1},"coordinates":[2355,671]},{"type":"Point","properties":{"occ":1},"coordinates":[2355,671]},{"type":"Point","properties":{"occ":2},"coordinates":[2355,671]},{"type":"Point","properties":{"occ":1},"coordinates":[2355,671]},{"type":"Point","properties":{"occ":1},"coordinates":[2355,671]},{"type":"Point","properties":{"occ":1},"coordinates":[2355,671]},{"type":"Point","properties":{"occ":1},"coordinates":[2355,671]},{"type":"Point","properties":{"occ":1},"coordinates":[2355,671]},{"type":"Point","properties":{"occ":1},"coordinates":[2355,671]},{"type":"Point","properties":{"occ":1},"coordinates":[2355,671]},{"type":"Point","properties":{"occ":1},"coordinates":[2355,671]},{"type":"Point","properties":{"occ":1},"coordinates":[2355,671]},{"type":"Point","properties":{"occ":1},"coordinates":[2355,671]},{"type":"Point","properties":{"occ":2},"coordinates":[2355,671]},{"type":"Point","properties":{"occ":2},"coordinates":[2355,671]},{"type":"Point","properties":{"occ":1},"coordinates":[2355,671]},{"type":"Point","properties":{"occ":1},"coordinates":[2355,671]},{"type":"Point","properties":{"occ":1},"coordinates":[2355,671]},{"type":"Point","properties":{"occ":1},"coordinates":[2301,704]},{"type":"Point","properties":{"occ":1},"coordinates":[2301,704]},{"type":"Point","properties":{"occ":1},"coordinates":[2301,704]},{"type":"Point","properties":{"occ":1},"coordinates":[2301,704]},{"type":"Point","properties":{"occ":1},"coordinates":[2301,704]},{"type":"Point","properties":{"occ":1},"coordinates":[2301,704]},{"type":"Point","properties":{"occ":1},"coordinates":[2301,704]},{"type":"Point","properties":{"occ":1},"coordinates":[2301,704]},{"type":"Point","properties":{"occ":1},"coordinates":[2301,704]},{"type":"Point","properties":{"occ":1},"coordinates":[2360,588]},{"type":"Point","properties":{"occ":1},"coordinates":[2360,588]},{"type":"Point","properties":{"occ":1},"coordinates":[2360,588]},{"type":"Point","properties":{"occ":1},"coordinates":[2360,588]},{"type":"Point","properties":{"occ":1},"coordinates":[2342,619]},{"type":"Point","properties":{"occ":1},"coordinates":[2355,671]},{"type":"Point","properties":{"occ":1},"coordinates":[2355,671]},{"type":"Point","properties":{"occ":1},"coordinates":[2355,671]},{"type":"Point","properties":{"occ":1},"coordinates":[2355,671]},{"type":"Point","properties":{"occ":1},"coordinates":[2355,671]},{"type":"Point","properties":{"occ":1},"coordinates":[2313,691]},{"type":"Point","properties":{"occ":1},"coordinates":[2313,691]},{"type":"Point","properties":{"occ":1},"coordinates":[2355,671]},{"type":"Point","properties":{"occ":1},"coordinates":[2353,624]},{"type":"Point","properties":{"occ":1},"coordinates":[2355,671]},{"type":"Point","properties":{"occ":2},"coordinates":[2355,671]},{"type":"Point","properties":{"occ":2},"coordinates":[2355,671]},{"type":"Point","properties":{"occ":2},"coordinates":[2355,671]},{"type":"Point","properties":{"occ":1},"coordinates":[2355,671]},{"type":"Point","properties":{"occ":1},"coordinates":[2355,671]},{"type":"Point","properties":{"occ":2},"coordinates":[2355,671]},{"type":"Point","properties":{"occ":1},"coordinates":[2355,671]},{"type":"Point","properties":{"occ":2},"coordinates":[2355,671]},{"type":"Point","properties":{"occ":2},"coordinates":[2358,600]},{"type":"Point","properties":{"occ":4},"coordinates":[2358,601]},{"type":"Point","properties":{"occ":1},"coordinates":[2358,600]},{"type":"Point","properties":{"occ":1},"coordinates":[2355,671]},{"type":"Point","properties":{"occ":1},"coordinates":[2269,727]},{"type":"Point","properties":{"occ":1},"coordinates":[2355,671]},{"type":"Point","properties":{"occ":2},"coordinates":[2471,595]},{"type":"Point","properties":{"occ":1},"coordinates":[2471,595]},{"type":"Point","properties":{"occ":1},"coordinates":[2471,595]},{"type":"Point","properties":{"occ":1},"coordinates":[2471,595]},{"type":"Point","properties":{"occ":1},"coordinates":[2471,595]},{"type":"Point","properties":{"occ":2},"coordinates":[2471,595]},{"type":"Point","properties":{"occ":3},"coordinates":[2471,595]},{"type":"Point","properties":{"occ":7},"coordinates":[2471,595]},{"type":"Point","properties":{"occ":8},"coordinates":[2471,595]},{"type":"Point","properties":{"occ":7},"coordinates":[2471,595]},{"type":"Point","properties":{"occ":1},"coordinates":[2471,595]},{"type":"Point","properties":{"occ":1},"coordinates":[2509,616]},{"type":"Point","properties":{"occ":6},"coordinates":[2509,616]},{"type":"Point","properties":{"occ":6},"coordinates":[2509,616]},{"type":"Point","properties":{"occ":6},"coordinates":[2509,616]},{"type":"Point","properties":{"occ":1},"coordinates":[2509,616]},{"type":"Point","properties":{"occ":1},"coordinates":[2509,616]},{"type":"Point","properties":{"occ":2},"coordinates":[2509,616]},{"type":"Point","properties":{"occ":2},"coordinates":[2509,616]},{"type":"Point","properties":{"occ":4},"coordinates":[2509,616]},{"type":"Point","properties":{"occ":4},"coordinates":[2509,616]},{"type":"Point","properties":{"occ":6},"coordinates":[2509,616]},{"type":"Point","properties":{"occ":17},"coordinates":[2509,616]},{"type":"Point","properties":{"occ":6},"coordinates":[2509,616]},{"type":"Point","properties":{"occ":3},"coordinates":[2509,616]},{"type":"Point","properties":{"occ":9},"coordinates":[2509,616]},{"type":"Point","properties":{"occ":2},"coordinates":[2509,616]},{"type":"Point","properties":{"occ":1},"coordinates":[2509,616]},{"type":"Point","properties":{"occ":2},"coordinates":[2509,616]},{"type":"Point","properties":{"occ":2},"coordinates":[2509,616]},{"type":"Point","properties":{"occ":1},"coordinates":[2509,616]},{"type":"Point","properties":{"occ":2},"coordinates":[2453,452]},{"type":"Point","properties":{"occ":2},"coordinates":[2453,452]},{"type":"Point","properties":{"occ":3},"coordinates":[2453,452]},{"type":"Point","properties":{"occ":2},"coordinates":[2453,452]},{"type":"Point","properties":{"occ":2},"coordinates":[2380,470]},{"type":"Point","properties":{"occ":9},"coordinates":[2380,470]},{"type":"Point","properties":{"occ":4},"coordinates":[2380,470]},{"type":"Point","properties":{"occ":4},"coordinates":[2380,470]},{"type":"Point","properties":{"occ":3},"coordinates":[2380,470]},{"type":"Point","properties":{"occ":1},"coordinates":[2380,470]},{"type":"Point","properties":{"occ":1},"coordinates":[2380,470]},{"type":"Point","properties":{"occ":2},"coordinates":[2380,470]},{"type":"Point","properties":{"occ":2},"coordinates":[2380,470]},{"type":"Point","properties":{"occ":5},"coordinates":[2380,470]},{"type":"Point","properties":{"occ":1},"coordinates":[2380,470]},{"type":"Point","properties":{"occ":2},"coordinates":[2412,414]},{"type":"Point","properties":{"occ":3},"coordinates":[2412,414]},{"type":"Point","properties":{"occ":5},"coordinates":[2412,414]},{"type":"Point","properties":{"occ":2},"coordinates":[2412,414]},{"type":"Point","properties":{"occ":3},"coordinates":[2412,414]},{"type":"Point","properties":{"occ":2},"coordinates":[2425,393]},{"type":"Point","properties":{"occ":2},"coordinates":[2412,414]},{"type":"Point","properties":{"occ":1},"coordinates":[2425,393]},{"type":"Point","properties":{"occ":2},"coordinates":[2412,414]},{"type":"Point","properties":{"occ":3},"coordinates":[2412,414]},{"type":"Point","properties":{"occ":2},"coordinates":[2425,393]},{"type":"Point","properties":{"occ":4},"coordinates":[2412,414]},{"type":"Point","properties":{"occ":1},"coordinates":[2412,414]},{"type":"Point","properties":{"occ":2},"coordinates":[2449,355]},{"type":"Point","properties":{"occ":1},"coordinates":[2449,355]},{"type":"Point","properties":{"occ":2},"coordinates":[2449,355]},{"type":"Point","properties":{"occ":1},"coordinates":[2449,355]},{"type":"Point","properties":{"occ":4},"coordinates":[2449,355]},{"type":"Point","properties":{"occ":2},"coordinates":[2449,355]},{"type":"Point","properties":{"occ":3},"coordinates":[2449,355]},{"type":"Point","properties":{"occ":1},"coordinates":[2449,355]},{"type":"Point","properties":{"occ":2},"coordinates":[2449,355]},{"type":"Point","properties":{"occ":1},"coordinates":[2449,355]},{"type":"Point","properties":{"occ":3},"coordinates":[2461,330]},{"type":"Point","properties":{"occ":3},"coordinates":[2461,330]},{"type":"Point","properties":{"occ":2},"coordinates":[2461,330]},{"type":"Point","properties":{"occ":4},"coordinates":[2461,330]},{"type":"Point","properties":{"occ":1},"coordinates":[2311,588]},{"type":"Point","properties":{"occ":2},"coordinates":[2311,588]},{"type":"Point","properties":{"occ":4},"coordinates":[2311,588]},{"type":"Point","properties":{"occ":2},"coordinates":[2311,588]},{"type":"Point","properties":{"occ":9},"coordinates":[2380,470]},{"type":"Point","properties":{"occ":2},"coordinates":[2380,470]},{"type":"Point","properties":{"occ":3},"coordinates":[2380,470]},{"type":"Point","properties":{"occ":1},"coordinates":[2280,587]}]}},"arcs":[],"transform":{"scale":[0.010267693569356936,0.004792145614561456],"translate":[-141.5,34.5]}}